[
    {
      "name": "Classic White Shirt",
      "description": "A crisp and clean white shirt, perfect for formal occasions.",
      "category": "Shirts",
      "size": "M",
      "condition": "Like New",
      "location": "Quebec City, Canada",
      "images": ["https://example.com/images/white-shirt.jpg"],
      "owner": "64dca1c98f8b4b8f9c8e4c6d",
      "isAvailable": true,
      "views": 12
    },
    {
      "name": "Casual Blue Jeans",
      "description": "Comfortable blue jeans for everyday wear.",
      "category": "Pants",
      "size": "L",
      "condition": "Good",
      "location": "Montreal, Canada",
      "images": ["https://example.com/images/blue-jeans.jpg"],
      "owner": "64dca1c98f8b4b8f9c8e4c6e",
      "isAvailable": true,
      "views": 34
    },
    {
      "name": "Leather Jacket",
      "description": "A stylish leather jacket for the winter season.",
      "category": "Jackets",
      "size": "XL",
      "condition": "New",
      "location": "Toronto, Canada",
      "images": ["https://example.com/images/leather-jacket.jpg"],
      "owner": "64dca1c98f8b4b8f9c8e4c6f",
      "isAvailable": true,
      "views": 50
    },
    {
      "name": "Running Shoes",
      "description": "Lightweight running shoes for all terrains.",
      "category": "Shoes",
      "size": "42",
      "condition": "Good",
      "location": "Vancouver, Canada",
      "images": ["https://example.com/images/running-shoes.jpg"],
      "owner": "64dca1c98f8b4b8f9c8e4c70",
      "isAvailable": false,
      "views": 78
    },
    {
      "name": "Silk Scarf",
      "description": "Elegant silk scarf for all occasions.",
      "category": "Accessories",
      "size": "Custom",
      "condition": "New",
      "location": "Calgary, Canada",
      "images": ["https://example.com/images/silk-scarf.jpg"],
      "owner": "64dca1c98f8b4b8f9c8e4c71",
      "isAvailable": true,
      "views": 23
    },
    {
      "name": "Vintage Denim Jacket",
      "description": "Classic denim jacket with a retro vibe.",
      "category": "Jackets",
      "size": "S",
      "condition": "Worn",
      "location": "Edmonton, Canada",
      "images": ["https://example.com/images/denim-jacket.jpg"],
      "owner": "64dca1c98f8b4b8f9c8e4c72",
      "isAvailable": true,
      "views": 45
    },
    {
      "name": "Striped T-Shirt",
      "description": "Casual striped t-shirt for everyday use.",
      "category": "Shirts",
      "size": "L",
      "condition": "Good",
      "location": "Halifax, Canada",
      "images": ["https://example.com/images/striped-tshirt.jpg"],
      "owner": "64dca1c98f8b4b8f9c8e4c73",
      "isAvailable": false,
      "views": 18
    },
    {
      "name": "Elegant Evening Gown",
      "description": "A stunning gown for special events and parties.",
      "category": "Other",
      "size": "M",
      "condition": "Like New",
      "location": "Ottawa, Canada",
      "images": ["https://example.com/images/evening-gown.jpg"],
      "owner": "64dca1c98f8b4b8f9c8e4c74",
      "isAvailable": true,
      "views": 65
    },
    {
      "name": "Winter Boots",
      "description": "Durable winter boots with excellent grip.",
      "category": "Shoes",
      "size": "43",
      "condition": "Like New",
      "location": "Quebec City, Canada",
      "images": ["https://example.com/images/winter-boots.jpg"],
      "owner": "64dca1c98f8b4b8f9c8e4c75",
      "isAvailable": true,
      "views": 55
    },
    {
      "name": "Casual Hoodie",
      "description": "A cozy hoodie for casual wear.",
      "category": "Other",
      "size": "XL",
      "condition": "Good",
      "location": "Montreal, Canada",
      "images": ["https://example.com/images/hoodie.jpg"],
      "owner": "64dca1c98f8b4b8f9c8e4c76",
      "isAvailable": true,
      "views": 40
    },
    {
      "name": "Formal Black Trousers",
      "description": "Elegant black trousers for formal settings.",
      "category": "Pants",
      "size": "M",
      "condition": "New",
      "location": "Toronto, Canada",
      "images": ["https://example.com/images/black-trousers.jpg"],
      "owner": "64dca1c98f8b4b8f9c8e4c77",
      "isAvailable": false,
      "views": 30
    },
    {
      "name": "Sports Cap",
      "description": "Adjustable sports cap for outdoor activities.",
      "category": "Accessories",
      "size": "Custom",
      "condition": "Good",
      "location": "Vancouver, Canada",
      "images": ["https://example.com/images/sports-cap.jpg"],
      "owner": "64dca1c98f8b4b8f9c8e4c78",
      "isAvailable": true,
      "views": 20
    },
    {
      "name": "Knit Sweater",
      "description": "Warm and cozy knit sweater for winter.",
      "category": "Other",
      "size": "L",
      "condition": "New",
      "location": "Calgary, Canada",
      "images": ["https://example.com/images/knit-sweater.jpg"],
      "owner": "64dca1c98f8b4b8f9c8e4c79",
      "isAvailable": true,
      "views": 28
    },
    {
      "name": "Classic Black Belt",
      "description": "High-quality leather belt in classic black.",
      "category": "Accessories",
      "size": "Custom",
      "condition": "New",
      "location": "Edmonton, Canada",
      "images": ["https://example.com/images/black-belt.jpg"],
      "owner": "64dca1c98f8b4b8f9c8e4c80",
      "isAvailable": true,
      "views": 10
    },
    {
      "name": "Elegant High Heels",
      "description": "Stylish high heels for special events.",
      "category": "Shoes",
      "size": "37",
      "condition": "Like New",
      "location": "Halifax, Canada",
      "images": ["https://example.com/images/high-heels.jpg"],
      "owner": "64dca1c98f8b4b8f9c8e4c81",
      "isAvailable": false,
      "views": 65
    }
  ]
  